pulumi_digitalocean/__init__.py
pulumi_digitalocean/_enums.py
pulumi_digitalocean/_inputs.py
pulumi_digitalocean/_utilities.py
pulumi_digitalocean/app.py
pulumi_digitalocean/cdn.py
pulumi_digitalocean/certificate.py
pulumi_digitalocean/container_registry.py
pulumi_digitalocean/container_registry_docker_credentials.py
pulumi_digitalocean/custom_image.py
pulumi_digitalocean/database_cluster.py
pulumi_digitalocean/database_connection_pool.py
pulumi_digitalocean/database_db.py
pulumi_digitalocean/database_firewall.py
pulumi_digitalocean/database_kafka_config.py
pulumi_digitalocean/database_kafka_schema_registry.py
pulumi_digitalocean/database_kafka_topic.py
pulumi_digitalocean/database_mongodb_config.py
pulumi_digitalocean/database_mysql_config.py
pulumi_digitalocean/database_online_migration.py
pulumi_digitalocean/database_opensearch_config.py
pulumi_digitalocean/database_postgresql_config.py
pulumi_digitalocean/database_redis_config.py
pulumi_digitalocean/database_replica.py
pulumi_digitalocean/database_user.py
pulumi_digitalocean/database_valkey_config.py
pulumi_digitalocean/dns_record.py
pulumi_digitalocean/domain.py
pulumi_digitalocean/droplet.py
pulumi_digitalocean/droplet_autoscale.py
pulumi_digitalocean/droplet_snapshot.py
pulumi_digitalocean/firewall.py
pulumi_digitalocean/floating_ip.py
pulumi_digitalocean/floating_ip_assignment.py
pulumi_digitalocean/genai_agent.py
pulumi_digitalocean/genai_agent_knowledge_base_attachment.py
pulumi_digitalocean/genai_agent_route.py
pulumi_digitalocean/genai_function.py
pulumi_digitalocean/genai_indexing_job_cancel.py
pulumi_digitalocean/genai_knowledge_base.py
pulumi_digitalocean/genai_knowledge_base_data_source.py
pulumi_digitalocean/genai_openai_api_key.py
pulumi_digitalocean/get_account.py
pulumi_digitalocean/get_app.py
pulumi_digitalocean/get_certificate.py
pulumi_digitalocean/get_container_registry.py
pulumi_digitalocean/get_database_ca.py
pulumi_digitalocean/get_database_cluster.py
pulumi_digitalocean-4.55.0.dist-info/METADATA
pulumi_digitalocean-4.55.0.dist-info/WHEEL
pulumi_digitalocean-4.55.0.dist-info/top_level.txt
pulumi_digitalocean-4.55.0.dist-info/RECORD
